odoo/addons/account_voucher_viewer/__init__.py
odoo/addons/account_voucher_viewer/__manifest__.py
odoo/addons/account_voucher_viewer/security/ir.model.access.csv
odoo/addons/account_voucher_viewer/static/description/icon.png
odoo12_addon_account_voucher_viewer-12.0.1.0.0.99.dev2.dist-info/METADATA
odoo12_addon_account_voucher_viewer-12.0.1.0.0.99.dev2.dist-info/WHEEL
odoo12_addon_account_voucher_viewer-12.0.1.0.0.99.dev2.dist-info/top_level.txt
odoo12_addon_account_voucher_viewer-12.0.1.0.0.99.dev2.dist-info/RECORD
